{
    "name": "5dim_decoration",
    "version": "2.0.0",
    "factorio_version": "2.0",
    "title": "5Dim's mod - Decoration",
    "author": "5Dim",
    "contact": "https://github.com/McGuten/Factorio5DimMods/issues",
    "homepage": "https://mods.factorio.com/user/McGuten",
    "description": "Decoration module for 5Dim's mod\n\rAdd decorative elements to personalize your factory\n\rThis mod includes:\n\r- Placeable numbers (0-9)\n\r- Placeable letters (A-Z)\n\r- Decorative tiles\n\r- Signs and markers for factory organization",
    "dependencies": ["5dim_core >= 2.0.42"]
}
